LICENSE
MANIFEST.in
README.rst
setup.py
supercsv/__init__.py
supercsv.egg-info/PKG-INFO
supercsv.egg-info/SOURCES.txt
supercsv.egg-info/dependency_links.txt
supercsv.egg-info/not-zip-safe
supercsv.egg-info/top_level.txt