Metadata-Version: 1.0
Name: supercsv
Version: 0.1
Summary: csv unicode
Home-page: UNKNOWN
Author: UNKNOWN
Author-email: UNKNOWN
License: PSF
Platform: any
Classifier: Development Status :: 5 - Production/Stable
Classifier: Intended Audience :: Developers
Classifier: License :: Other/Proprietary License
Classifier: Operating System :: OS Independent
Classifier: Programming Language :: Python
